episol/.epipy.py.swp
episol/.gvv.tip3p-MgCl.01A.txt.swp
episol/__init__.py
episol/epipy.py
episol/epipy.py~
episol/gvv.tip3p-MgCl.01A.txt
episol/gvv.tip3p.1DDRISM.01A.txt
episol/methane.gro
episol/methane.solute
episol/methane.top
episol/old_epipy.py
episol/tip3p-MgCl-amber18-full.gaff
episol/tip3p-amber14.01A.gaff
episol-0.1.2.dist-info/METADATA
episol-0.1.2.dist-info/WHEEL
episol-0.1.2.dist-info/licenses/LICENSE.md
episol-0.1.2.dist-info/RECORD
