Metadata-Version: 2.4
Name: episol
Version: 0.1.2
Summary: Python interface for EPISOL 3DRISM calculations
Project-URL: Homepage, https://github.com/EPISOLrelease/EPIPY
Project-URL: Issues, https://github.com/EPISOLrelease/EPIPY/issues
Author-email: Peter Swanson <pcswanson@wisc.edu>, Siqin Cao <scao@wisc.edu>
License-Expression: GPL-3.0-only
License-File: LICENSE.md
Classifier: Operating System :: OS Independent
Classifier: Programming Language :: Python :: 3
Requires-Python: >=3.10
